smart_arg.py
smart_arg-0.1.1.dist-info/LICENSE.md
smart_arg-0.1.1.dist-info/METADATA
smart_arg-0.1.1.dist-info/NOTICE
smart_arg-0.1.1.dist-info/WHEEL
smart_arg-0.1.1.dist-info/top_level.txt
smart_arg-0.1.1.dist-info/RECORD
