Metadata-Version: 2.1
Name: smart-arg
Version: 0.1.1
Summary: Argument class <=> Human friendly cli
Home-page: UNKNOWN
Author: 
Author-email: 
License: BSD-2-CLAUSE
Download-URL: https://pypi.python.org/pypi/smart-arg
Project-URL: Source, https://github.com/linkedin/smart-arg.git
Project-URL: Tracker, https://github.com/linkedin/smart-arg/issues
Keywords: typing,argument parser,reverse argument parser,human friendly,configuration (de)serialization,python,cli
Platform: UNKNOWN
Classifier: Programming Language :: Python
Classifier: Programming Language :: Python :: 3
Classifier: Operating System :: OS Independent
Classifier: License :: OSI Approved
Classifier: Typing :: Typed
Requires-Python: >=3.6
